Processador 2/memoria.v

module memoria(pc, out);

    input [5:0] pc;
    output reg [15:0] out;

    reg [15:0] mem[63:0];

    initial begin
        // // Teste 1: 35 + 50 - 62 + 50 = 72
        // mem[0] = 16'b1010000000100010; // LDI R0, 34
        // mem[1] = 16'b1010010000110010; // LDI R1, 50
        // mem[2] = 16'b0000000010000000; // ADD R0 = R0 + R1
        // mem[3] = 16'b1010100000111110; // LDI R2, 62
        // mem[4] = 16'b0010000100000000; // SUB R0 = R0 - R2
        // mem[5] = 16'b0000000010000000; // ADD R0 = R0 + R1
        // mem[6] = 16'b1110110000000000; // REP R3 = R0
        // mem[7] = 16'b1000110000000000; // OUT R3
        // mem[8] = 16'b0110000000000000; // HALT

        // Teste 2: 6 * 6 = 36
        mem[0] = 16'b1010010000000001; // LDI R1, 1
        mem[1] = 16'b1010100000000101; // LDI R2, 5
        mem[2] = 16'b1010110000000110; // LDI R3, 6
        mem[3] = 16'b1111000110000000; // REP R4 = R3
        mem[4] = 16'b0000111000000000; // ADD R3 = R3 + R4
        mem[5] = 16'b0010100010000000; // SUB R2 = R2 - R1
        mem[6] = 16'b1100100000000010; // BNE R2 2
        mem[7] = 16'b1100001111111101; // BNE R0 -3
        mem[8] = 16'b1000110000000000; // OUT R3
        mem[9] = 16'b0110000000000000; // HALT
    end

    always @(pc) begin
        out = mem[pc];
    end
endmodule

Processador 2/pc.v

module pc(cont, jmp, pc);

    input [1:0] cont;
    input [5:0] jmp;
    output reg [5:0] pc;
    
    initial pc = -1;

    always @(cont) begin
        if (cont == 2'b00 && jmp == 0) pc = pc + 1;
        else pc = pc + jmp;
    end
endmodule

Processador 2/counter.v



module counter (clock, clear, out);

	input clock, clear;
	output reg [1:0] out;

	initial #2 out = 2'b00;
	
	always @(posedge clock) begin
	
		if(clear == 1)
			out <= 2'b00;
		else
			out <= out + 1'b1;
	end

endmodule

Processador 2/ula.v



module ula (rA, b, opSelect, rG);

	input [15:0] rA, b;
	input [2:0] opSelect;
	output reg [15:0] rG;
	
	parameter REP = 3'b111;
	parameter LDI = 3'b101;
	parameter ADD = 3'b000;
	parameter SUB = 3'b001;
	parameter NAN = 3'b010;
	parameter OUT = 3'b100;
	
	always @* begin
	
		case (opSelect)
			ADD: rG = rA + b;
			SUB: rG = rA - b;
			NAN: rG = ~(rA & b);
			default: rG = rA;
		endcase
	
	end

endmodule

Processador 2/registrador.v


module registrador(in, enable, out, clock);

	input [15:0] in;
	input enable, clock;
	output reg [15:0] out;
	
	initial out = 16'b0000000000000000;
	
	always @(posedge clock) begin
		if (enable == 1) out = in;
	end

endmodule

Processador 2/mux4x2.v


module mux4x2(i0, i1, i2, i3, key, out);

    input [15:0] i0, i1, i2, i3;
	input [1:0] key;
	output reg [15:0] out;

    always @* begin
        case (key)
            3'b00: out = i0;
            3'b01: out = i1;
            3'b10: out = i2;
            3'b11: out = i3;
        endcase
    end
endmodule

Processador 2/extensor.v

module extensor(in, out);
    input [15:0] in;
    output reg [15:0] out;

    always @* begin
        if (in[9] == 1)
            out = {6'b111111, in[9:0]};
        else out = {6'b000000, in[9:0]};
    end
endmodule

Processador 2/mux8x3.v


module mux8x3(i0, i1, i2, i3, i4, i5, i6, i7, key, out);

    input [15:0] i0, i1, i2, i3, i4, i5, i6, i7;
	input [2:0] key;
	output reg [15:0] out;

    always @* begin
        case (key)
            3'b000: out = i0;
            3'b001: out = i1;
            3'b010: out = i2;
            3'b011: out = i3;
            3'b100: out = i4;
            3'b101: out = i5;
            3'b110: out = i6;
            3'b111: out = i7;
        endcase
    end
endmodule

Processador 2/bancoReg.v

module bancoReg(in, out, key, w, clock);
    input [15:0] in;
    input [2:0] key;
    input w, clock;
    output [15:0] out;

    wire [15:0] outR0, outR1, outR2, outR3, outR4, outR5, outR6, outR7;
    reg r0e, r1e, r2e, r3e, r4e, r5e, r6e, r7e;

    mux8x3 mOut (.i0(outR0), .i1(outR1), .i2(outR2), .i3(outR3), .i4(outR4), .i5(outR5), .i6(outR6), .i7(outR7), .key(key), .out(out));

    registrador re0 (.in(in), .enable(r0e), .out(outR0), .clock(clock));
	registrador re1 (.in(in), .enable(r1e), .out(outR1), .clock(clock));
	registrador re2 (.in(in), .enable(r2e), .out(outR2), .clock(clock));
	registrador re3 (.in(in), .enable(r3e), .out(outR3), .clock(clock));
	registrador re4 (.in(in), .enable(r4e), .out(outR4), .clock(clock));
	registrador re5 (.in(in), .enable(r5e), .out(outR5), .clock(clock));
	registrador re6 (.in(in), .enable(r6e), .out(outR6), .clock(clock));
	registrador re7 (.in(in), .enable(r7e), .out(outR7), .clock(clock));

    initial begin
        r0e = 0;
        r1e = 0;
        r2e = 0;
        r3e = 0;
        r4e = 0;
        r5e = 0;
        r6e = 0;
        r7e = 0;
    end

    always @* begin
        r0e = 0;
        r1e = 0;
        r2e = 0;
        r3e = 0;
        r4e = 0;
        r5e = 0;
        r6e = 0;
        r7e = 0;
        if (w == 1) begin
            case (key)
                3'b000: r0e = 1;
                3'b001: r1e = 1;
                3'b010: r2e = 1;
                3'b011: r3e = 1;
                3'b100: r4e = 1;
                3'b101: r5e = 1;
                3'b110: r6e = 1;
                3'b111: r7e = 1;
            endcase 
        end
    end

endmodule

Processador 2/processor.v



module processor (clock, bus, exit);
	input clock;
	output reg [15:0] bus;
	output reg exit;

	parameter ADD = 3'b000; // Instrução de soma
	parameter SUB = 3'b001; // Instrução de subtração
	parameter NAN = 3'b010; // Instrução de NAND
	parameter HLT = 3'b011; // Instrução de halt
	parameter OUT = 3'b100; // Instrução de output
	parameter LDI = 3'b101; // Instrução de load imediato
	parameter BNE = 3'b110; // Instrução de jump
	parameter REP = 3'b111; // Instrução de substituição

	wire [15:0] outMulti, outBReg, outRR, outRA, outUla, outEx, outMem;
	wire [5:0] progCounter;
	wire [1:0] outCont;


	reg [5:0] jmp;
	reg [2:0] regSelect;
	reg [1:0] muxSelect; // 00 = BReg, 01 = Reg R, 10 = imediato
	reg w, rRe, rAe, clearCont;



	bancoReg b1 (.in(outMulti), .out(outBReg), .key(regSelect), .w(w), .clock(clock));

	extensor ex(.in(outMem), .out(outEx));

	mux4x2 m1 (.i0(outBReg), .i1(outRR), .i2(outEx), .i3(16'b0000000000000000), .key(muxSelect), .out(outMulti));

	registrador rR(.in(outUla), .enable(rRe), .out(outRR), .clock(clock));
	registrador rA(.in(outMulti), .enable(rAe), .out(outRA), .clock(clock));

	ula u1 (.rA(outRA), .b(outMulti), .opSelect(outMem[15:13]), .rG(outUla));

	counter c1 (.clock(clock), .clear(clearCont), .out(outCont));

	pc p1 (.cont(outCont), .jmp(jmp), .pc(progCounter));

	memoria mem1 (.pc(progCounter), .out(outMem));

	initial begin
		exit = 0;
		clearCont = 1;
		jmp = 0;
	end

	always @(clock) begin
		case (outCont)
			2'b00: begin
				// Desabilita a escrita nos registradores e reseta o multiplexador
				jmp = 0;
				w = 0;
				rAe = 0;
				rRe = 0;
				muxSelect = 0;
				clearCont = 0;
				// Descobre o primeiro operando
				regSelect = outMem[12:10]; // O banco de registradores seleciona o registrador que será lido
			end
			2'b01: begin
				// Ativa o registrador A para receber o primeiro operando
				rAe = 1;
				if (outMem[15:13] == REP) regSelect = outMem[9:7]; // Se a instrução for repetição, o primeiro operando é o registrador selecionado
				else if (outMem[15:13] == LDI) muxSelect = 2'b10; // Se a instrução for load imediato, o segundo operando é o imediato
			end
			2'b10: begin
				// Desativa o registrador A e ativa o registrador R para receber o resultado da ULA
				rAe = 0;
				rRe = 1;
				// Se a instrução for ADD, SUB ou NAN, o segundo operando é o registrador selecionado
				if (outMem[15:13] == ADD || outMem[15:13] == SUB || outMem[15:13] == NAN) begin
					regSelect = outMem[9:7];
					muxSelect = 0;
				end
			end
			2'b11: begin
				// Desativa o registrador R e seleciona ele como saída do multiplexador
				rRe = 0;
				muxSelect = 2'b01;
				// Se a instrução for BNE e o resultado da ULA for 0, o jump é ativado
				if (outMem[15:13] == BNE && outRR == 0) begin
					muxSelect = 2'b10;
					jmp = outMulti[5:0];
				end
				// Se a instrução for OUT, o barramento é atualizado
				else if (outMem[15:13] == OUT) bus = outMulti;
				else if (outMem[15:13] == HLT) exit = 1;
				// Caso contrário, escrevemos no registrador selecionado
				else begin
					regSelect = outMem[12:10];
					w = 1;
				end
				// Reseta o contador
				clearCont = 1;
			end
		endcase
	end
endmodule

Processador 2/testbench.v


module testbench (cout);

	output reg [15:0] cout;
	reg clock = 1;
	reg [15:0] iin;
	wire exit;
	
	wire [15:0] bus;
	
	always #1 clock = !clock;
	
	initial $dumpfile("testbench.vcd");
	initial $dumpvars(0, testbench);

	processor p(clock, bus, exit);
	
	initial begin
		cout = bus;
	end

	always @* begin
		if (exit == 1) $finish;
	end
endmodule

Processador 2/testbench.vcd
$date
	Sat Jul  6 20:47:40 2024
$end
$version
	Icarus Verilog
$end
$timescale
	1s
$end
$scope module testbench $end
$var wire 1 ! exit $end
$var wire 16 " bus [15:0] $end
$var reg 1 # clock $end
$var reg 16 $ cout [15:0] $end
$scope module p $end
$var wire 1 # clock $end
$var wire 6 % progCounter [5:0] $end
$var wire 16 & outUla [15:0] $end
$var wire 16 ' outRR [15:0] $end
$var wire 16 ( outRA [15:0] $end
$var wire 16 ) outMulti [15:0] $end
$var wire 16 * outMem [15:0] $end
$var wire 16 + outEx [15:0] $end
$var wire 2 , outCont [1:0] $end
$var wire 16 - outBReg [15:0] $end
$var parameter 3 . ADD $end
$var parameter 3 / BNE $end
$var parameter 3 0 HLT $end
$var parameter 3 1 LDI $end
$var parameter 3 2 NAN $end
$var parameter 3 3 OUT $end
$var parameter 3 4 REP $end
$var parameter 3 5 SUB $end
$var reg 16 6 bus [15:0] $end
$var reg 1 7 clearCont $end
$var reg 1 ! exit $end
$var reg 6 8 jmp [5:0] $end
$var reg 2 9 muxSelect [1:0] $end
$var reg 1 : rAe $end
$var reg 1 ; rRe $end
$var reg 3 < regSelect [2:0] $end
$var reg 1 = w $end
$scope module b1 $end
$var wire 1 # clock $end
$var wire 3 > key [2:0] $end
$var wire 1 = w $end
$var wire 16 ? outR7 [15:0] $end
$var wire 16 @ outR6 [15:0] $end
$var wire 16 A outR5 [15:0] $end
$var wire 16 B outR4 [15:0] $end
$var wire 16 C outR3 [15:0] $end
$var wire 16 D outR2 [15:0] $end
$var wire 16 E outR1 [15:0] $end
$var wire 16 F outR0 [15:0] $end
$var wire 16 G out [15:0] $end
$var wire 16 H in [15:0] $end
$var reg 1 I r0e $end
$var reg 1 J r1e $end
$var reg 1 K r2e $end
$var reg 1 L r3e $end
$var reg 1 M r4e $end
$var reg 1 N r5e $end
$var reg 1 O r6e $end
$var reg 1 P r7e $end
$scope module mOut $end
$var wire 3 Q key [2:0] $end
$var wire 16 R i7 [15:0] $end
$var wire 16 S i6 [15:0] $end
$var wire 16 T i5 [15:0] $end
$var wire 16 U i4 [15:0] $end
$var wire 16 V i3 [15:0] $end
$var wire 16 W i2 [15:0] $end
$var wire 16 X i1 [15:0] $end
$var wire 16 Y i0 [15:0] $end
$var reg 16 Z out [15:0] $end
$upscope $end
$scope module re0 $end
$var wire 1 # clock $end
$var wire 1 I enable $end
$var wire 16 [ in [15:0] $end
$var reg 16 \ out [15:0] $end
$upscope $end
$scope module re1 $end
$var wire 1 # clock $end
$var wire 1 J enable $end
$var wire 16 ] in [15:0] $end
$var reg 16 ^ out [15:0] $end
$upscope $end
$scope module re2 $end
$var wire 1 # clock $end
$var wire 1 K enable $end
$var wire 16 _ in [15:0] $end
$var reg 16 ` out [15:0] $end
$upscope $end
$scope module re3 $end
$var wire 1 # clock $end
$var wire 1 L enable $end
$var wire 16 a in [15:0] $end
$var reg 16 b out [15:0] $end
$upscope $end
$scope module re4 $end
$var wire 1 # clock $end
$var wire 1 M enable $end
$var wire 16 c in [15:0] $end
$var reg 16 d out [15:0] $end
$upscope $end
$scope module re5 $end
$var wire 1 # clock $end
$var wire 1 N enable $end
$var wire 16 e in [15:0] $end
$var reg 16 f out [15:0] $end
$upscope $end
$scope module re6 $end
$var wire 1 # clock $end
$var wire 1 O enable $end
$var wire 16 g in [15:0] $end
$var reg 16 h out [15:0] $end
$upscope $end
$scope module re7 $end
$var wire 1 # clock $end
$var wire 1 P enable $end
$var wire 16 i in [15:0] $end
$var reg 16 j out [15:0] $end
$upscope $end
$upscope $end
$scope module c1 $end
$var wire 1 7 clear $end
$var wire 1 # clock $end
$var reg 2 k out [1:0] $end
$upscope $end
$scope module ex $end
$var wire 16 l in [15:0] $end
$var reg 16 m out [15:0] $end
$upscope $end
$scope module m1 $end
$var wire 16 n i0 [15:0] $end
$var wire 16 o i2 [15:0] $end
$var wire 16 p i3 [15:0] $end
$var wire 2 q key [1:0] $end
$var wire 16 r i1 [15:0] $end
$var reg 16 s out [15:0] $end
$upscope $end
$scope module mem1 $end
$var wire 6 t pc [5:0] $end
$var reg 16 u out [15:0] $end
$upscope $end
$scope module p1 $end
$var wire 2 v cont [1:0] $end
$var wire 6 w jmp [5:0] $end
$var reg 6 x pc [5:0] $end
$upscope $end
$scope module rA $end
$var wire 1 # clock $end
$var wire 1 : enable $end
$var wire 16 y in [15:0] $end
$var reg 16 z out [15:0] $end
$upscope $end
$scope module rR $end
$var wire 1 # clock $end
$var wire 1 ; enable $end
$var wire 16 { in [15:0] $end
$var reg 16 | out [15:0] $end
$upscope $end
$scope module u1 $end
$var wire 16 } b [15:0] $end
$var wire 3 ~ opSelect [2:0] $end
$var wire 16 !" rA [15:0] $end
$var parameter 3 "" ADD $end
$var parameter 3 #" LDI $end
$var parameter 3 $" NAN $end
$var parameter 3 %" OUT $end
$var parameter 3 &" REP $end
$var parameter 3 '" SUB $end
$var reg 16 (" rG [15:0] $end
$upscope $end
$upscope $end
$upscope $end
$enddefinitions $end
$comment Show the parameter values. $end
$dumpall
b1 '"
b111 &"
b100 %"
b10 $"
b101 #"
b0 ""
b1 5
b111 4
b100 3
b10 2
b101 1
b11 0
b110 /
b0 .
$end
#0
$dumpvars
b0 ("
b0 !"
b101 ~
bx }
b0 |
b0 {
b0 z
bx y
b0 x
b0 w
b0 v
b1010000000000000 u
b0 t
bx s
b0 r
bx q
b0 p
b0 o
bx n
b0 m
b1010000000000000 l
b0 k
b0 j
bx i
b0 h
bx g
b0 f
bx e
b0 d
bx c
b0 b
bx a
b0 `
bx _
b0 ^
bx ]
b0 \
bx [
bx Z
b0 Y
b0 X
b0 W
b0 V
b0 U
b0 T
b0 S
b0 R
bx Q
0P
0O
0N
0M
0L
0K
0J
0I
bx H
bx G
b0 F
b0 E
b0 D
b0 C
b0 B
b0 A
b0 @
b0 ?
bx >
x=
bx <
x;
x:
bx 9
b0 8
17
bx 6
bx -
b0 ,
b0 +
b1010000000000000 *
bx )
b0 (
b0 '
b0 &
b0 %
bx $
1#
bx "
0!
$end
#1
b0 )
b0 H
b0 [
b0 ]
b0 _
b0 a
b0 c
b0 e
b0 g
b0 i
b0 s
b0 y
b0 }
b0 -
b0 G
b0 Z
b0 n
b0 <
b0 >
b0 Q
07
b0 9
b0 q
0;
0:
0=
0#
#2
b1 ,
b1 k
b1 v
1#
#3
b10 9
b10 q
1:
0#
#4
b10 ,
b10 k
b10 v
1#
#5
1;
0:
0#
#6
b11 ,
b11 k
b11 v
1#
#7
1I
17
1=
b1 9
b1 q
0;
0#
#8
b1 +
b1 m
b1 o
b1010010000000001 *
b1010010000000001 l
b1010010000000001 u
b1 %
b1 t
b1 x
b0 ,
b0 k
b0 v
1#
#9
0I
b1 <
b1 >
b1 Q
07
b0 9
b0 q
0=
0#
#10
b1 ,
b1 k
b1 v
1#
#11
b1 )
b1 H
b1 [
b1 ]
b1 _
b1 a
b1 c
b1 e
b1 g
b1 i
b1 s
b1 y
b1 }
b10 9
b10 q
1:
0#
#12
b10 ,
b10 k
b10 v
b1 &
b1 {
b1 ("
b1 (
b1 z
b1 !"
1#
#13
1;
0:
0#
#14
b11 ,
b11 k
b11 v
b1 '
b1 r
b1 |
1#
#15
1J
17
1=
b1 9
b1 q
0;
0#
#16
b101 +
b101 m
b101 o
b1010100000000101 *
b1010100000000101 l
b1010100000000101 u
b10 %
b10 t
b10 x
b0 ,
b0 k
b0 v
b1 -
b1 G
b1 Z
b1 n
b1 E
b1 X
b1 ^
1#
#17
b0 )
b0 H
b0 [
b0 ]
b0 _
b0 a
b0 c
b0 e
b0 g
b0 i
b0 s
b0 y
b0 }
b0 -
b0 G
b0 Z
b0 n
0J
b10 <
b10 >
b10 Q
07
b0 9
b0 q
0=
0#
#18
b1 ,
b1 k
b1 v
1#
#19
b101 )
b101 H
b101 [
b101 ]
b101 _
b101 a
b101 c
b101 e
b101 g
b101 i
b101 s
b101 y
b101 }
b10 9
b10 q
1:
0#
#20
b10 ,
b10 k
b10 v
b101 &
b101 {
b101 ("
b101 (
b101 z
b101 !"
1#
#21
1;
0:
0#
#22
b11 ,
b11 k
b11 v
b101 '
b101 r
b101 |
1#
#23
1K
17
1=
b1 9
b1 q
0;
0#
#24
b110 +
b110 m
b110 o
b1010110000000110 *
b1010110000000110 l
b1010110000000110 u
b11 %
b11 t
b11 x
b0 ,
b0 k
b0 v
b101 -
b101 G
b101 Z
b101 n
b101 D
b101 W
b101 `
1#
#25
b0 )
b0 H
b0 [
b0 ]
b0 _
b0 a
b0 c
b0 e
b0 g
b0 i
b0 s
b0 y
b0 }
b0 -
b0 G
b0 Z
b0 n
0K
b11 <
b11 >
b11 Q
07
b0 9
b0 q
0=
0#
#26
b1 ,
b1 k
b1 v
1#
#27
b110 )
b110 H
b110 [
b110 ]
b110 _
b110 a
b110 c
b110 e
b110 g
b110 i
b110 s
b110 y
b110 }
b10 9
b10 q
1:
0#
#28
b10 ,
b10 k
b10 v
b110 &
b110 {
b110 ("
b110 (
b110 z
b110 !"
1#
#29
1;
0:
0#
#30
b11 ,
b11 k
b11 v
b110 '
b110 r
b110 |
1#
#31
1L
17
1=
b1 9
b1 q
0;
0#
#32
b111 ~
b110000000 +
b110000000 m
b110000000 o
b1111000110000000 *
b1111000110000000 l
b1111000110000000 u
b100 %
b100 t
b100 x
b0 ,
b0 k
b0 v
b110 -
b110 G
b110 Z
b110 n
b110 C
b110 V
b110 b
1#
#33
b0 )
b0 H
b0 [
b0 ]
b0 _
b0 a
b0 c
b0 e
b0 g
b0 i
b0 s
b0 y
b0 }
b0 -
b0 G
b0 Z
b0 n
0L
b100 <
b100 >
b100 Q
07
b0 9
b0 q
0=
0#
#34
b1 ,
b1 k
b1 v
1#
#35
b110 )
b110 H
b110 [
b110 ]
b110 _
b110 a
b110 c
b110 e
b110 g
b110 i
b110 s
b110 y
b110 }
b110 -
b110 G
b110 Z
b110 n
b11 <
b11 >
b11 Q
1:
0#
#36
b10 ,
b10 k
b10 v
1#
#37
1;
0:
0#
#38
b11 ,
b11 k
b11 v
1#
#39
b0 -
b0 G
b0 Z
b0 n
1M
17
1=
b100 <
b100 >
b100 Q
b1 9
b1 q
0;
0#
#40
b1100 &
b1100 {
b1100 ("
b0 ~
b1111111000000000 +
b1111111000000000 m
b1111111000000000 o
b111000000000 *
b111000000000 l
b111000000000 u
b101 %
b101 t
b101 x
b0 ,
b0 k
b0 v
b110 -
b110 G
b110 Z
b110 n
b110 B
b110 U
b110 d
1#
#41
0M
b11 <
b11 >
b11 Q
07
b0 9
b0 q
0=
0#
#42
b1 ,
b1 k
b1 v
1#
#43
1:
0#
#44
b10 ,
b10 k
b10 v
1#
#45
b100 <
b100 >
b100 Q
1;
0:
0#
#46
b11 ,
b11 k
b11 v
b1100 '
b1100 r
b1100 |
1#
#47
b10010 &
b10010 {
b10010 ("
1L
b1100 )
b1100 H
b1100 [
b1100 ]
b1100 _
b1100 a
b1100 c
b1100 e
b1100 g
b1100 i
b1100 s
b1100 y
b1100 }
17
1=
b11 <
b11 >
b11 Q
b1 9
b1 q
0;
0#
#48
b1111111111111010 &
b1111111111111010 {
b1111111111111010 ("
b1 ~
b10000000 +
b10000000 m
b10000000 o
b10100010000000 *
b10100010000000 l
b10100010000000 u
b110 %
b110 t
b110 x
b0 ,
b0 k
b0 v
b1100 -
b1100 G
b1100 Z
b1100 n
b1100 C
b1100 V
b1100 b
1#
#49
b1 &
b1 {
b1 ("
b101 )
b101 H
b101 [
b101 ]
b101 _
b101 a
b101 c
b101 e
b101 g
b101 i
b101 s
b101 y
b101 }
b101 -
b101 G
b101 Z
b101 n
0L
b10 <
b10 >
b10 Q
07
b0 9
b0 q
0=
0#
#50
b1 ,
b1 k
b1 v
1#
#51
1:
0#
#52
b10 ,
b10 k
b10 v
b0 &
b0 {
b0 ("
b101 (
b101 z
b101 !"
1#
#53
b100 &
b100 {
b100 ("
b1 )
b1 H
b1 [
b1 ]
b1 _
b1 a
b1 c
b1 e
b1 g
b1 i
b1 s
b1 y
b1 }
b1 -
b1 G
b1 Z
b1 n
b1 <
b1 >
b1 Q
1;
0:
0#
#54
b11 ,
b11 k
b11 v
b100 '
b100 r
b100 |
1#
#55
b1 &
b1 {
b1 ("
b101 -
b101 G
b101 Z
b101 n
1K
b100 )
b100 H
b100 [
b100 ]
b100 _
b100 a
b100 c
b100 e
b100 g
b100 i
b100 s
b100 y
b100 }
17
1=
b10 <
b10 >
b10 Q
b1 9
b1 q
0;
0#
#56
b101 &
b101 {
b101 ("
b110 ~
b10 +
b10 m
b10 o
b1100100000000010 *
b1100100000000010 l
b1100100000000010 u
b111 %
b111 t
b111 x
b0 ,
b0 k
b0 v
b100 -
b100 G
b100 Z
b100 n
b100 D
b100 W
b100 `
1#
#57
0K
07
b0 9
b0 q
0=
0#
#58
b1 ,
b1 k
b1 v
1#
#59
1:
0#
#60
b10 ,
b10 k
b10 v
b100 &
b100 {
b100 ("
b100 (
b100 z
b100 !"
1#
#61
1;
0:
0#
#62
b11 ,
b11 k
b11 v
1#
#63
1K
17
1=
b1 9
b1 q
0;
0#
#64
b1111111111111101 +
b1111111111111101 m
b1111111111111101 o
b1100001111111101 *
b1100001111111101 l
b1100001111111101 u
b1000 %
b1000 t
b1000 x
b0 ,
b0 k
b0 v
1#
#65
b0 )
b0 H
b0 [
b0 ]
b0 _
b0 a
b0 c
b0 e
b0 g
b0 i
b0 s
b0 y
b0 }
b0 -
b0 G
b0 Z
b0 n
0K
b0 <
b0 >
b0 Q
07
b0 9
b0 q
0=
0#
#66
b1 ,
b1 k
b1 v
1#
#67
1:
0#
#68
b10 ,
b10 k
b10 v
b0 &
b0 {
b0 ("
b0 (
b0 z
b0 !"
1#
#69
1;
0:
0#
#70
b11 ,
b11 k
b11 v
b0 '
b0 r
b0 |
1#
#71
b1111111111111101 )
b1111111111111101 H
b1111111111111101 [
b1111111111111101 ]
b1111111111111101 _
b1111111111111101 a
b1111111111111101 c
b1111111111111101 e
b1111111111111101 g
b1111111111111101 i
b1111111111111101 s
b1111111111111101 y
b1111111111111101 }
17
b10 9
b10 q
0;
0#
#72
b1111111000000000 &
b1111111000000000 {
b1111111000000000 ("
b1111111000000000 )
b1111111000000000 H
b1111111000000000 [
b1111111000000000 ]
b1111111000000000 _
b1111111000000000 a
b1111111000000000 c
b1111111000000000 e
b1111111000000000 g
b1111111000000000 i
b1111111000000000 s
b1111111000000000 y
b1111111000000000 }
b0 ~
b1111111000000000 +
b1111111000000000 m
b1111111000000000 o
b111000000000 *
b111000000000 l
b111000000000 u
b101 %
b101 t
b101 x
b0 ,
b0 k
b0 v
b111101 8
b111101 w
b10 9
b10 q
1#
#73
b1100 &
b1100 {
b1100 ("
b1100 -
b1100 G
b1100 Z
b1100 n
b1100 )
b1100 H
b1100 [
b1100 ]
b1100 _
b1100 a
b1100 c
b1100 e
b1100 g
b1100 i
b1100 s
b1100 y
b1100 }
b11 <
b11 >
b11 Q
07
b0 9
b0 q
b0 8
b0 w
0#
#74
b1 ,
b1 k
b1 v
1#
#75
1:
0#
#76
b10 ,
b10 k
b10 v
b11000 &
b11000 {
b11000 ("
b1100 (
b1100 z
b1100 !"
1#
#77
b10010 &
b10010 {
b10010 ("
b110 )
b110 H
b110 [
b110 ]
b110 _
b110 a
b110 c
b110 e
b110 g
b110 i
b110 s
b110 y
b110 }
b110 -
b110 G
b110 Z
b110 n
b100 <
b100 >
b100 Q
1;
0:
0#
#78
b11 ,
b11 k
b11 v
b10010 '
b10010 r
b10010 |
1#
#79
b11110 &
b11110 {
b11110 ("
b1100 -
b1100 G
b1100 Z
b1100 n
1L
b10010 )
b10010 H
b10010 [
b10010 ]
b10010 _
b10010 a
b10010 c
b10010 e
b10010 g
b10010 i
b10010 s
b10010 y
b10010 }
17
1=
b11 <
b11 >
b11 Q
b1 9
b1 q
0;
0#
#80
b1111111111111010 &
b1111111111111010 {
b1111111111111010 ("
b1 ~
b10000000 +
b10000000 m
b10000000 o
b10100010000000 *
b10100010000000 l
b10100010000000 u
b110 %
b110 t
b110 x
b0 ,
b0 k
b0 v
b10010 -
b10010 G
b10010 Z
b10010 n
b10010 C
b10010 V
b10010 b
1#
#81
b1000 &
b1000 {
b1000 ("
b100 )
b100 H
b100 [
b100 ]
b100 _
b100 a
b100 c
b100 e
b100 g
b100 i
b100 s
b100 y
b100 }
b100 -
b100 G
b100 Z
b100 n
0L
b10 <
b10 >
b10 Q
07
b0 9
b0 q
0=
0#
#82
b1 ,
b1 k
b1 v
1#
#83
1:
0#
#84
b10 ,
b10 k
b10 v
b0 &
b0 {
b0 ("
b100 (
b100 z
b100 !"
1#
#85
b11 &
b11 {
b11 ("
b1 )
b1 H
b1 [
b1 ]
b1 _
b1 a
b1 c
b1 e
b1 g
b1 i
b1 s
b1 y
b1 }
b1 -
b1 G
b1 Z
b1 n
b1 <
b1 >
b1 Q
1;
0:
0#
#86
b11 ,
b11 k
b11 v
b11 '
b11 r
b11 |
1#
#87
b1 &
b1 {
b1 ("
b100 -
b100 G
b100 Z
b100 n
1K
b11 )
b11 H
b11 [
b11 ]
b11 _
b11 a
b11 c
b11 e
b11 g
b11 i
b11 s
b11 y
b11 }
17
1=
b10 <
b10 >
b10 Q
b1 9
b1 q
0;
0#
#88
b100 &
b100 {
b100 ("
b110 ~
b10 +
b10 m
b10 o
b1100100000000010 *
b1100100000000010 l
b1100100000000010 u
b111 %
b111 t
b111 x
b0 ,
b0 k
b0 v
b11 -
b11 G
b11 Z
b11 n
b11 D
b11 W
b11 `
1#
#89
0K
07
b0 9
b0 q
0=
0#
#90
b1 ,
b1 k
b1 v
1#
#91
1:
0#
#92
b10 ,
b10 k
b10 v
b11 &
b11 {
b11 ("
b11 (
b11 z
b11 !"
1#
#93
1;
0:
0#
#94
b11 ,
b11 k
b11 v
1#
#95
1K
17
1=
b1 9
b1 q
0;
0#
#96
b1111111111111101 +
b1111111111111101 m
b1111111111111101 o
b1100001111111101 *
b1100001111111101 l
b1100001111111101 u
b1000 %
b1000 t
b1000 x
b0 ,
b0 k
b0 v
1#
#97
b0 )
b0 H
b0 [
b0 ]
b0 _
b0 a
b0 c
b0 e
b0 g
b0 i
b0 s
b0 y
b0 }
b0 -
b0 G
b0 Z
b0 n
0K
b0 <
b0 >
b0 Q
07
b0 9
b0 q
0=
0#
#98
b1 ,
b1 k
b1 v
1#
#99
1:
0#
#100
b10 ,
b10 k
b10 v
b0 &
b0 {
b0 ("
b0 (
b0 z
b0 !"
1#
#101
1;
0:
0#
#102
b11 ,
b11 k
b11 v
b0 '
b0 r
b0 |
1#
#103
b1111111111111101 )
b1111111111111101 H
b1111111111111101 [
b1111111111111101 ]
b1111111111111101 _
b1111111111111101 a
b1111111111111101 c
b1111111111111101 e
b1111111111111101 g
b1111111111111101 i
b1111111111111101 s
b1111111111111101 y
b1111111111111101 }
17
b10 9
b10 q
0;
0#
#104
b1111111000000000 &
b1111111000000000 {
b1111111000000000 ("
b1111111000000000 )
b1111111000000000 H
b1111111000000000 [
b1111111000000000 ]
b1111111000000000 _
b1111111000000000 a
b1111111000000000 c
b1111111000000000 e
b1111111000000000 g
b1111111000000000 i
b1111111000000000 s
b1111111000000000 y
b1111111000000000 }
b0 ~
b1111111000000000 +
b1111111000000000 m
b1111111000000000 o
b111000000000 *
b111000000000 l
b111000000000 u
b101 %
b101 t
b101 x
b0 ,
b0 k
b0 v
b111101 8
b111101 w
b10 9
b10 q
1#
#105
b10010 &
b10010 {
b10010 ("
b10010 -
b10010 G
b10010 Z
b10010 n
b10010 )
b10010 H
b10010 [
b10010 ]
b10010 _
b10010 a
b10010 c
b10010 e
b10010 g
b10010 i
b10010 s
b10010 y
b10010 }
b11 <
b11 >
b11 Q
07
b0 9
b0 q
b0 8
b0 w
0#
#106
b1 ,
b1 k
b1 v
1#
#107
1:
0#
#108
b10 ,
b10 k
b10 v
b100100 &
b100100 {
b100100 ("
b10010 (
b10010 z
b10010 !"
1#
#109
b11000 &
b11000 {
b11000 ("
b110 )
b110 H
b110 [
b110 ]
b110 _
b110 a
b110 c
b110 e
b110 g
b110 i
b110 s
b110 y
b110 }
b110 -
b110 G
b110 Z
b110 n
b100 <
b100 >
b100 Q
1;
0:
0#
#110
b11 ,
b11 k
b11 v
b11000 '
b11000 r
b11000 |
1#
#111
b101010 &
b101010 {
b101010 ("
b10010 -
b10010 G
b10010 Z
b10010 n
1L
b11000 )
b11000 H
b11000 [
b11000 ]
b11000 _
b11000 a
b11000 c
b11000 e
b11000 g
b11000 i
b11000 s
b11000 y
b11000 }
17
1=
b11 <
b11 >
b11 Q
b1 9
b1 q
0;
0#
